prometrix/__init__.py
prometrix/auth.py
prometrix/connect/__init__.py
prometrix/connect/aws_connect.py
prometrix/connect/custom_connect.py
prometrix/exceptions.py
prometrix/models/prometheus_config.py
prometrix/models/prometheus_result.py
prometrix/utils.py
prometrix-0.2.9.dist-info/METADATA
prometrix-0.2.9.dist-info/WHEEL
prometrix-0.2.9.dist-info/licenses/LICENSE.md
prometrix-0.2.9.dist-info/RECORD
