Metadata-Version: 2.4
Name: prometrix
Version: 0.2.9
Summary: A Python Prometheus client for all Prometheus instances.
License-File: LICENSE.md
Author: Avi Kotlicky
Author-email: avi@robusta.dev
Requires-Python: >=3.10,<4.0
Classifier: Programming Language :: Python :: 3
Classifier: Programming Language :: Python :: 3.10
Classifier: Programming Language :: Python :: 3.11
Classifier: Programming Language :: Python :: 3.12
Classifier: Programming Language :: Python :: 3.13
Classifier: Programming Language :: Python :: 3.14
Requires-Dist: boto3 (>=1.38,<2.0)
Requires-Dist: botocore (>=1.38,<2.0)
Requires-Dist: fonttools (>=4.43.0,<5.0.0)
Requires-Dist: idna (>=3.7,<4.0)
Requires-Dist: pillow (>=10.3.0,<11.0.0)
Requires-Dist: prometheus-api-client (>=0.5.3,<0.6.0)
Requires-Dist: pydantic (>=1.8.1,<3)
Requires-Dist: requests (>2.32.4)
Requires-Dist: urllib3 (>=2.6.0,<3.0.0)
Requires-Dist: zipp (>=3.20.1,<4.0.0)
Project-URL: Bug Tracker, https://github.com/robusta-dev/prometrix/issues
Project-URL: Homepage, https://github.com/robusta-dev/prometrix
